ca_certificates/__init__.py
xx_ent_wiki_sm-99.0.0.dist-info/METADATA
xx_ent_wiki_sm-99.0.0.dist-info/WHEEL
xx_ent_wiki_sm-99.0.0.dist-info/top_level.txt
xx_ent_wiki_sm-99.0.0.dist-info/RECORD
